<?xml version="1.0" ?>
<data>
  <!--NOTE: This is an ** Autogenerated file **-->
  <!--NOTE: Sector size is 4096bytes-->
  <program SECTOR_SIZE_IN_BYTES="4096" file_sector_offset="0" filename="tz.mbn" label="tz" num_partition_sectors="1024" partofsingleimage="false" physical_partition_number="4" readbackverify="false" size_in_KB="4096.0" sparse="false" start_byte_hex="0x6000" start_sector="6"/>
  <program SECTOR_SIZE_IN_BYTES="4096" file_sector_offset="0" filename="aop.mbn" label="aop" num_partition_sectors="128" partofsingleimage="false" physical_partition_number="4" readbackverify="false" size_in_KB="512.0" sparse="false" start_byte_hex="0x406000" start_sector="1030"/>
  <program SECTOR_SIZE_IN_BYTES="4096" file_sector_offset="0" filename="abl.elf" label="abl" num_partition_sectors="1024" partofsingleimage="false" physical_partition_number="4" readbackverify="false" size_in_KB="4096.0" sparse="false" start_byte_hex="0x486000" start_sector="1158"/>
  <program SECTOR_SIZE_IN_BYTES="4096" file_sector_offset="0" filename="" label="devinfo" num_partition_sectors="1" partofsingleimage="false" physical_partition_number="4" readbackverify="false" size_in_KB="4.0" sparse="false" start_byte_hex="0x886000" start_sector="2182"/>
  <program SECTOR_SIZE_IN_BYTES="4096" file_sector_offset="0" filename="" label="bluetooth" num_partition_sectors="256" partofsingleimage="false" physical_partition_number="4" readbackverify="false" size_in_KB="1024.0" sparse="false" start_byte_hex="0x887000" start_sector="2183"/>
  <program SECTOR_SIZE_IN_BYTES="4096" file_sector_offset="0" filename="" label="mdtpsecapp" num_partition_sectors="1024" partofsingleimage="false" physical_partition_number="4" readbackverify="false" size_in_KB="4096.0" sparse="false" start_byte_hex="0x987000" start_sector="2439"/>
  <program SECTOR_SIZE_IN_BYTES="4096" file_sector_offset="0" filename="" label="mdtp" num_partition_sectors="8192" partofsingleimage="false" physical_partition_number="4" readbackverify="false" size_in_KB="32768.0" sparse="false" start_byte_hex="0xd87000" start_sector="3463"/>
  <program SECTOR_SIZE_IN_BYTES="4096" file_sector_offset="0" filename="bksecapp.mbn" label="bksecapp" num_partition_sectors="96" partofsingleimage="false" physical_partition_number="4" readbackverify="false" size_in_KB="384.0" sparse="false" start_byte_hex="0x2d87000" start_sector="11655"/>
  <program SECTOR_SIZE_IN_BYTES="4096" file_sector_offset="0" filename="km4.mbn" label="keymaster" num_partition_sectors="128" partofsingleimage="false" physical_partition_number="4" readbackverify="false" size_in_KB="512.0" sparse="false" start_byte_hex="0x2de7000" start_sector="11751"/>
  <program SECTOR_SIZE_IN_BYTES="4096" file_sector_offset="0" filename="" label="apdp" num_partition_sectors="64" partofsingleimage="false" physical_partition_number="4" readbackverify="false" size_in_KB="256.0" sparse="false" start_byte_hex="0x2e67000" start_sector="11879"/>
  <program SECTOR_SIZE_IN_BYTES="4096" file_sector_offset="0" filename="" label="dpo" num_partition_sectors="1" partofsingleimage="false" physical_partition_number="4" readbackverify="false" size_in_KB="4.0" sparse="false" start_byte_hex="0x2ea7000" start_sector="11943"/>
  <program SECTOR_SIZE_IN_BYTES="4096" file_sector_offset="0" filename="" label="spunvm" num_partition_sectors="2048" partofsingleimage="false" physical_partition_number="4" readbackverify="false" size_in_KB="8192.0" sparse="false" start_byte_hex="0x2ea8000" start_sector="11944"/>
  <program SECTOR_SIZE_IN_BYTES="4096" file_sector_offset="0" filename="" label="splash" num_partition_sectors="8356" partofsingleimage="false" physical_partition_number="4" readbackverify="false" size_in_KB="33424.0" sparse="false" start_byte_hex="0x36a8000" start_sector="13992"/>
  <program SECTOR_SIZE_IN_BYTES="4096" file_sector_offset="0" filename="" label="limits" num_partition_sectors="1" partofsingleimage="false" physical_partition_number="4" readbackverify="false" size_in_KB="4.0" sparse="false" start_byte_hex="0x574c000" start_sector="22348"/>
  <program SECTOR_SIZE_IN_BYTES="4096" file_sector_offset="0" filename="" label="limits-cdsp" num_partition_sectors="1" partofsingleimage="false" physical_partition_number="4" readbackverify="false" size_in_KB="4.0" sparse="false" start_byte_hex="0x574d000" start_sector="22349"/>
  <program SECTOR_SIZE_IN_BYTES="4096" file_sector_offset="0" filename="" label="toolsfv" num_partition_sectors="512" partofsingleimage="false" physical_partition_number="4" readbackverify="false" size_in_KB="2048.0" sparse="false" start_byte_hex="0x574e000" start_sector="22350"/>
  <program SECTOR_SIZE_IN_BYTES="4096" file_sector_offset="0" filename="logfs_ufs_8mb.bin" label="logfs" num_partition_sectors="2048" partofsingleimage="false" physical_partition_number="4" readbackverify="false" size_in_KB="8192.0" sparse="false" start_byte_hex="0x594e000" start_sector="22862"/>
  <program SECTOR_SIZE_IN_BYTES="4096" file_sector_offset="0" filename="" label="logdump" num_partition_sectors="16384" partofsingleimage="false" physical_partition_number="4" readbackverify="false" size_in_KB="65536.0" sparse="false" start_byte_hex="0x614e000" start_sector="24910"/>
  <program SECTOR_SIZE_IN_BYTES="4096" file_sector_offset="0" filename="devcfg.mbn" label="devcfg" num_partition_sectors="32" partofsingleimage="false" physical_partition_number="4" readbackverify="false" size_in_KB="128.0" sparse="false" start_byte_hex="0xa14e000" start_sector="41294"/>
  <program SECTOR_SIZE_IN_BYTES="4096" file_sector_offset="0" filename="storsec.mbn" label="storsec" num_partition_sectors="128" partofsingleimage="false" physical_partition_number="4" readbackverify="false" size_in_KB="512.0" sparse="false" start_byte_hex="0xa16e000" start_sector="41326"/>
  <program SECTOR_SIZE_IN_BYTES="4096" file_sector_offset="0" filename="" label="vbmeta_system" num_partition_sectors="16" partofsingleimage="false" physical_partition_number="4" readbackverify="false" size_in_KB="64.0" sparse="false" start_byte_hex="0xa1ee000" start_sector="41454"/>
  <program SECTOR_SIZE_IN_BYTES="4096" file_sector_offset="0" filename="" label="vbmeta" num_partition_sectors="16" partofsingleimage="false" physical_partition_number="4" readbackverify="false" size_in_KB="64.0" sparse="false" start_byte_hex="0xa1fe000" start_sector="41470"/>
  <program SECTOR_SIZE_IN_BYTES="4096" file_sector_offset="0" filename="qupv3fw.elf" label="qupfw" num_partition_sectors="20" partofsingleimage="false" physical_partition_number="4" readbackverify="false" size_in_KB="80.0" sparse="false" start_byte_hex="0xa20e000" start_sector="41486"/>
  <program SECTOR_SIZE_IN_BYTES="4096" file_sector_offset="0" filename="uefi_sec.mbn" label="uefisecapp" num_partition_sectors="512" partofsingleimage="false" physical_partition_number="4" readbackverify="false" size_in_KB="2048.0" sparse="false" start_byte_hex="0xa222000" start_sector="41506"/>
  <program SECTOR_SIZE_IN_BYTES="4096" file_sector_offset="0" filename="" label="questdatafv" num_partition_sectors="4096" partofsingleimage="false" physical_partition_number="4" readbackverify="false" size_in_KB="16384.0" sparse="false" start_byte_hex="0xa422000" start_sector="42018"/>
  <program SECTOR_SIZE_IN_BYTES="4096" file_sector_offset="0" filename="" label="dip" num_partition_sectors="256" partofsingleimage="false" physical_partition_number="4" readbackverify="false" size_in_KB="1024.0" sparse="false" start_byte_hex="0xb422000" start_sector="46114"/>
  <program SECTOR_SIZE_IN_BYTES="4096" file_sector_offset="0" filename="multi_image.mbn" label="multiimgoem" num_partition_sectors="8" partofsingleimage="false" physical_partition_number="4" readbackverify="false" size_in_KB="32.0" sparse="false" start_byte_hex="0xb522000" start_sector="46370"/>
  <program SECTOR_SIZE_IN_BYTES="4096" file_sector_offset="0" filename="sec.elf" label="secdata" num_partition_sectors="8" partofsingleimage="false" physical_partition_number="4" readbackverify="false" size_in_KB="32.0" sparse="false" start_byte_hex="0xb52a000" start_sector="46378"/>
  <program SECTOR_SIZE_IN_BYTES="4096" file_sector_offset="0" filename="" label="uefivarstore" num_partition_sectors="128" partofsingleimage="false" physical_partition_number="4" readbackverify="false" size_in_KB="512.0" sparse="false" start_byte_hex="0xb532000" start_sector="46386"/>
  <program SECTOR_SIZE_IN_BYTES="4096" file_sector_offset="0" filename="" label="vk" num_partition_sectors="512" partofsingleimage="false" physical_partition_number="4" readbackverify="false" size_in_KB="2048.0" sparse="false" start_byte_hex="0xb5b2000" start_sector="46514"/>
  <program SECTOR_SIZE_IN_BYTES="4096" file_sector_offset="0" filename="" label="btd" num_partition_sectors="512" partofsingleimage="false" physical_partition_number="4" readbackverify="false" size_in_KB="2048.0" sparse="false" start_byte_hex="0xb7b2000" start_sector="47026"/>
  <program SECTOR_SIZE_IN_BYTES="4096" file_sector_offset="0" filename="hyp.mbn" label="hyp" num_partition_sectors="256" partofsingleimage="false" physical_partition_number="4" readbackverify="false" size_in_KB="1024.0" sparse="false" start_byte_hex="0xb9b2000" start_sector="47538"/>
  <program SECTOR_SIZE_IN_BYTES="4096" file_sector_offset="0" filename="dspso.bin" label="dsp" num_partition_sectors="16384" partofsingleimage="false" physical_partition_number="4" readbackverify="false" size_in_KB="65536.0" sparse="false" start_byte_hex="0xbab2000" start_sector="47794"/>
  <program SECTOR_SIZE_IN_BYTES="4096" file_sector_offset="0" filename="tz_iccc.mbn" label="tziccc" num_partition_sectors="512" partofsingleimage="false" physical_partition_number="4" readbackverify="false" size_in_KB="2048.0" sparse="false" start_byte_hex="0xfab2000" start_sector="64178"/>
  <program SECTOR_SIZE_IN_BYTES="4096" file_sector_offset="0" filename="" label="last_parti" num_partition_sectors="0" partofsingleimage="false" physical_partition_number="4" readbackverify="false" size_in_KB="0" sparse="false" start_byte_hex="0xfcb2000" start_sector="64690"/>
  <program SECTOR_SIZE_IN_BYTES="4096" file_sector_offset="0" filename="gpt_main4.bin" label="PrimaryGPT" num_partition_sectors="6" partofsingleimage="true" physical_partition_number="4" readbackverify="false" size_in_KB="24.0" sparse="false" start_byte_hex="0x0" start_sector="0"/>
  <program SECTOR_SIZE_IN_BYTES="4096" file_sector_offset="0" filename="gpt_backup4.bin" label="BackupGPT" num_partition_sectors="5" partofsingleimage="true" physical_partition_number="4" readbackverify="false" size_in_KB="20.0" sparse="false" start_byte_hex="(4096*NUM_DISK_SECTORS)-20480." start_sector="NUM_DISK_SECTORS-5."/>
</data>
